jupyterlab_nb_venv_kernels_ui_extension/__init__.py
jupyterlab_nb_venv_kernels_ui_extension/_version.py
jupyterlab_nb_venv_kernels_ui_extension/handlers.py
jupyterlab_nb_venv_kernels_ui_extension-1.2.19.data/data/etc/jupyter/jupyter_server_config.d/jupyterlab_nb_venv_kernels_ui_extension.json
jupyterlab_nb_venv_kernels_ui_extension-1.2.19.data/data/share/jupyter/labextensions/jupyterlab_nb_venv_kernels_ui_extension/package.json
jupyterlab_nb_venv_kernels_ui_extension-1.2.19.data/data/share/jupyter/labextensions/jupyterlab_nb_venv_kernels_ui_extension/schemas/jupyterlab_nb_venv_kernels_ui_extension/package.json.orig
jupyterlab_nb_venv_kernels_ui_extension-1.2.19.data/data/share/jupyter/labextensions/jupyterlab_nb_venv_kernels_ui_extension/schemas/jupyterlab_nb_venv_kernels_ui_extension/plugin.json
jupyterlab_nb_venv_kernels_ui_extension-1.2.19.data/data/share/jupyter/labextensions/jupyterlab_nb_venv_kernels_ui_extension/static/509.4054a2704cb85fea5848.js
jupyterlab_nb_venv_kernels_ui_extension-1.2.19.data/data/share/jupyter/labextensions/jupyterlab_nb_venv_kernels_ui_extension/static/728.e3ba6055c3c897339850.js
jupyterlab_nb_venv_kernels_ui_extension-1.2.19.data/data/share/jupyter/labextensions/jupyterlab_nb_venv_kernels_ui_extension/static/remoteEntry.faba8407ea468b57284b.js
jupyterlab_nb_venv_kernels_ui_extension-1.2.19.data/data/share/jupyter/labextensions/jupyterlab_nb_venv_kernels_ui_extension/static/style.js
jupyterlab_nb_venv_kernels_ui_extension-1.2.19.data/data/share/jupyter/labextensions/jupyterlab_nb_venv_kernels_ui_extension/static/third-party-licenses.json
jupyterlab_nb_venv_kernels_ui_extension-1.2.19.data/data/share/jupyter/labextensions/jupyterlab_nb_venv_kernels_ui_extension/install.json
jupyterlab_nb_venv_kernels_ui_extension-1.2.19.dist-info/METADATA
jupyterlab_nb_venv_kernels_ui_extension-1.2.19.dist-info/WHEEL
jupyterlab_nb_venv_kernels_ui_extension-1.2.19.dist-info/licenses/LICENSE
jupyterlab_nb_venv_kernels_ui_extension-1.2.19.dist-info/RECORD
